prav-0.0.1.dist-info/METADATA
prav-0.0.1.dist-info/WHEEL
prav-0.0.1.dist-info/licenses/LICENSE-APACHE
prav-0.0.1.dist-info/licenses/LICENSE-MIT
prav/__init__.py
prav/__pycache__/__init__.cpython-310.pyc
prav/_prav.cpython-310-x86_64-linux-gnu.so
prav/_prav.pyi
prav/py.typed
prav-0.0.1.dist-info/RECORD
